requests_xml.py
requests_xml-0.2.3.dist-info/DESCRIPTION.rst
requests_xml-0.2.3.dist-info/METADATA
requests_xml-0.2.3.dist-info/RECORD
requests_xml-0.2.3.dist-info/WHEEL
requests_xml-0.2.3.dist-info/metadata.json
requests_xml-0.2.3.dist-info/top_level.txt
