Metadata-Version: 1.2
Name: requests-xml
Version: 0.2.3
Summary: XML Parsing for humans.
Home-page: https://github.com/erinxocon/requests-xml
Author: Erin O'Connell
Author-email: erinocon5@gmail.com
License: MIT
Platform: UNKNOWN
Classifier: License :: OSI Approved :: MIT License
Classifier: Programming Language :: Python
Classifier: Programming Language :: Python :: 3.6
Classifier: Programming Language :: Python :: Implementation :: CPython
Requires-Python: >=3.6.0
